setup_server.py
client/__init__.py
client/client.py
client/client/__init__.py
client/client/add_contact.py
client/client/database.py
client/client/del_contact.py
client/client/main_window.py
client/client/main_window_conv.py
client/client/start_dialog.py
client/client/transport.py
client/common/__init__.py
client/common/constants.py
client/common/decorators.py
client/common/descripts.py
client/common/errors.py
client/common/functions.py
client/common/metaclasses.py
client/logs/__init__.py
client/logs/config_client_log.py
client/logs/config_server_log.py
gb_message_server.egg-info/PKG-INFO
gb_message_server.egg-info/SOURCES.txt
gb_message_server.egg-info/dependency_links.txt
gb_message_server.egg-info/requires.txt
gb_message_server.egg-info/top_level.txt
server/__init__.py
server/server.py
server/common/__init__.py
server/common/constants.py
server/common/decorators.py
server/common/descripts.py
server/common/errors.py
server/common/functions.py
server/common/metaclasses.py
server/logs/__init__.py
server/logs/config_client_log.py
server/logs/config_server_log.py
server/server/__init__.py
server/server/add_user.py
server/server/config_window.py
server/server/core.py
server/server/db_server.py
server/server/main_window.py
server/server/remove_user.py
server/server/stat_window.py