Metadata-Version: 1.0
Name: gb-message-server
Version: 1.0.0
Summary: messanger_server
Home-page: UNKNOWN
Author: Oleg Spresov
Author-email: spoliv@rambler.ru
License: UNKNOWN
Platform: UNKNOWN
